bayesnestor/Nestor.py
bayesnestor/__init__.py
bayesnestor/algorithms/NestorAlgorithmManager.py
bayesnestor/algorithms/__init__.py
bayesnestor/core/BayesianNetwork.py
bayesnestor/core/CPTFactory.py
bayesnestor/core/ConditionalProbabilityTable.py
bayesnestor/core/DiscreteFactor.py
bayesnestor/core/ModelManager.py
bayesnestor/core/__init__.py
bayesnestor/core/backends/BackendFactory.py
bayesnestor/core/backends/BackendPgmpy.py
bayesnestor/core/backends/BackendPyAgrum.py
bayesnestor/core/backends/IBackend.py
bayesnestor/core/backends/__init__.py
bayesnestor/core/io/XmlBifReader.py
bayesnestor/core/io/__init__.py
bayesnestor/core/io/validation_files/__init__.py
bayesnestor/core/io/validation_files/schema_xmlbif.xsd
bayesnestor/core/io/validation_files/xmlbif.dtd
bayesnestor/data/__init__.py
bayesnestor/data/cn_LearnerCognitiveModel.xml
bayesnestor/data/cn_not_weighted.xml
bayesnestor/data/cn_weighted.xml
bayesnestor/reporting/BasicReporting.py
bayesnestor/reporting/DoWhyReporting.py
bayesnestor/reporting/IReporting.py
bayesnestor/reporting/ReportingContainers.py
bayesnestor/reporting/ReportingUtils.py
bayesnestor/reporting/VisualizeReporting.py
bayesnestor/reporting/__init__.py
bayesnestor/utils/ParameterContainer.py
bayesnestor/utils/Utils.py
bayesnestor/utils/__init__.py
examples/__init__.py
examples/example_access_backend_objs.py
examples/example_load_xmlbif.py
examples/example_nestor_generate_lepath.py
examples/examples_model_manager.py
examples/examples_reporting.py
tests/__init__.py
tests/conftest.py
tests/test_nestor.py
tests/algorithms/__init__.py
tests/algorithms/test_nestor_algorithm_manager.py
tests/core/__init__.py
tests/core/test_bayesian_network.py
tests/core/test_conditional_probability_table.py
tests/core/test_cpt_factory.py
tests/core/test_discrete_factor.py
tests/core/test_model_manager.py
tests/core/backends/__init__.py
tests/core/backends/test_backend_factory.py
tests/core/backends/test_backend_interface.py
tests/core/backends/test_backend_pgmpy.py
bayesNestor-0.1.7.dist-info/AUTHORS.rst
bayesNestor-0.1.7.dist-info/LICENSE.txt
bayesNestor-0.1.7.dist-info/METADATA
bayesNestor-0.1.7.dist-info/WHEEL
bayesNestor-0.1.7.dist-info/top_level.txt
bayesNestor-0.1.7.dist-info/RECORD
