Metadata-Version: 2.2
Name: bayesNestor
Version: 0.1.7
Summary: Nestor is a Bayesian Network implementation designed to dynamically generate personalized learning paths tailored to the unique psychological traits of each learner, optimizing educational outcomes.
Author: Robert Maier & Vamsi Krishna Nadimpalli
Author-email: robert.maier@othr.de & vamsi.nadimpalli@oth-regensburg.de
License: MIT
Classifier: Development Status :: 1 - Planning
Classifier: Intended Audience :: Science/Research
Classifier: License :: OSI Approved :: MIT License
Classifier: Operating System :: POSIX :: Linux
Classifier: Operating System :: Microsoft :: Windows
Classifier: Programming Language :: Python :: 3.10
Classifier: Programming Language :: Python :: 3.11
Requires-Python: >=3.10
License-File: LICENSE.txt
License-File: AUTHORS.rst
Requires-Dist: dowhy==0.11.1
Requires-Dist: lxml>=5.2
Requires-Dist: matplotlib>=3.9
Requires-Dist: networkx>=3.2
Requires-Dist: numpy==1.26.4
Requires-Dist: pandas>=2.2
Requires-Dist: pgmpy>=0.1.24
Requires-Dist: pyAgrum==1.15.0
Requires-Dist: pytest>=8.2
Requires-Dist: setuptools>=71.1
Requires-Dist: Sphinx>=7.4
Requires-Dist: torch==2.3.1
Requires-Dist: ipython>=8.16
Requires-Dist: tabulate>=0.9.0
Requires-Dist: dash>=2.16.0
Dynamic: author
Dynamic: author-email
Dynamic: classifier
Dynamic: description
Dynamic: description-content-type
Dynamic: license
Dynamic: requires-dist
Dynamic: requires-python
Dynamic: summary
